curequests/__about__.py
curequests/__init__.py
curequests/adapters.py
curequests/api.py
curequests/connection_pool.py
curequests/cuhttp.py
curequests/future.py
curequests/models.py
curequests/network.py
curequests/resource_pool.py
curequests/sessions.py
curequests/utils.py
curequests-0.4.1.dist-info/AUTHORS.md
curequests-0.4.1.dist-info/LICENSE
curequests-0.4.1.dist-info/METADATA
curequests-0.4.1.dist-info/WHEEL
curequests-0.4.1.dist-info/top_level.txt
curequests-0.4.1.dist-info/RECORD
