Metadata-Version: 2.1
Name: curequests
Version: 0.4.1
Summary: Curio + Requests: Async HTTP for Humans.
Home-page: https://github.com/guyskk/curequests
Author: guyskk
Author-email: guyskk@qq.com
License: MIT
Platform: UNKNOWN
Classifier: Intended Audience :: Developers
Classifier: License :: OSI Approved :: MIT License
Classifier: Operating System :: OS Independent
Classifier: Programming Language :: Python :: 3 :: Only
Classifier: Programming Language :: Python :: 3.6
Classifier: Topic :: Software Development :: Libraries :: Python Modules
Requires-Dist: httptools
Requires-Dist: yarl
Requires-Dist: curio
Requires-Dist: requests
Requires-Dist: namedlist
